steammaterials/STEAM_materials.py
steammaterials/STEAM_materials_ULTRA.py
steammaterials/STEAM_materials_functions.py
steammaterials/__init__.py
steammaterials/function_parameters.py
steammaterials/CFUN/BHAir_v1.dll
steammaterials/CFUN/BHIron2_v1.dll
steammaterials/CFUN/CFUN_CS_eJoule_v1.dll
steammaterials/CFUN/CFUN_CS_eJoule_v1_deriv.dll
steammaterials/CFUN/CFUN_CpHeMass_v1.dll
steammaterials/CFUN/CFUN_CvAg_v1.dll
steammaterials/CFUN/CFUN_CvAg_v1_deriv.dll
steammaterials/CFUN/CFUN_CvAl5083_v1.dll
steammaterials/CFUN/CFUN_CvAlAlloy_v1.dll
steammaterials/CFUN/CFUN_CvAl_v1.dll
steammaterials/CFUN/CFUN_CvAl_v1_deriv.dll
steammaterials/CFUN/CFUN_CvAl_v2_deriv.dll
steammaterials/CFUN/CFUN_CvBSCCO2212_v1.dll
steammaterials/CFUN/CFUN_CvBSCCO2212_v1_deriv.dll
steammaterials/CFUN/CFUN_CvBeCu_v1.dll
steammaterials/CFUN/CFUN_CvBeCu_v1_deriv.dll
steammaterials/CFUN/CFUN_CvBrass_v1.dll
steammaterials/CFUN/CFUN_CvBrass_v1_deriv.dll
steammaterials/CFUN/CFUN_CvCu_CUDI_v1.dll
steammaterials/CFUN/CFUN_CvCu_NIST_v1.dll
steammaterials/CFUN/CFUN_CvCu_v1.dll
steammaterials/CFUN/CFUN_CvCu_v1_deriv.dll
steammaterials/CFUN/CFUN_CvG10_v1.dll
steammaterials/CFUN/CFUN_CvG10_v1_deriv.dll
steammaterials/CFUN/CFUN_CvHast_v1.dll
steammaterials/CFUN/CFUN_CvHast_v1_deriv.dll
steammaterials/CFUN/CFUN_CvHeMass_v1.dll
steammaterials/CFUN/CFUN_CvHe_CUDI_v1.dll
steammaterials/CFUN/CFUN_CvHe_NIST_v1.dll
steammaterials/CFUN/CFUN_CvHe_v1.dll
steammaterials/CFUN/CFUN_CvIn_v0.dll
steammaterials/CFUN/CFUN_CvIn_v0_deriv.dll
steammaterials/CFUN/CFUN_CvKapton_v1.dll
steammaterials/CFUN/CFUN_CvKapton_v1_deriv.dll
steammaterials/CFUN/CFUN_CvNb3Sn_Arp_Knapp_v1.dll
steammaterials/CFUN/CFUN_CvNb3Sn_Arp_Knapp_v2.dll
steammaterials/CFUN/CFUN_CvNb3Sn_v1.dll
steammaterials/CFUN/CFUN_CvNb3Sn_v1_deriv.dll
steammaterials/CFUN/CFUN_CvNb3Sn_v2.dll
steammaterials/CFUN/CFUN_CvNbTi_CUDI_v1.dll
steammaterials/CFUN/CFUN_CvNbTi_v1.dll
steammaterials/CFUN/CFUN_CvNbTi_v1_deriv.dll
steammaterials/CFUN/CFUN_CvSS316_NIST_v1.dll
steam_materials-2026.1.2.dist-info/METADATA
steam_materials-2026.1.2.dist-info/WHEEL
steam_materials-2026.1.2.dist-info/top_level.txt
steam_materials-2026.1.2.dist-info/RECORD
