Metadata-Version: 2.4
Name: STEAM_materials
Version: 2026.1.2
Summary: Python wrapper for the steam materials package.
Home-page: https://gitlab.cern.ch/steam/steam-material-library
Author: STEAM Team
Author-email: steam-team@cern.ch
Keywords: STEAM,API,MATERIALS,CERN
Classifier: Programming Language :: Python :: 3.8
Requires-Python: >=3.8
Requires-Dist: numpy
Dynamic: author
Dynamic: author-email
Dynamic: classifier
Dynamic: description
Dynamic: description-content-type
Dynamic: home-page
Dynamic: keywords
Dynamic: requires-dist
Dynamic: requires-python
Dynamic: summary
